evokity/__init__.py
evokity/crossovers.py
evokity/mutations.py
evokity/selection.py
evokity-0.1.dist-info/WHEEL
evokity-0.1.dist-info/METADATA
evokity-0.1.dist-info/RECORD
