Metadata-Version: 2.1
Name: evokity
Version: 0.1
Summary: 
Author: amitkummer
Author-email: amit.kummer@gmail.com
Requires-Python: >=3.10,<4.0
Classifier: Programming Language :: Python :: 3
Classifier: Programming Language :: Python :: 3.10
Classifier: Programming Language :: Python :: 3.11
Requires-Dist: eckity (>=0.2.3,<0.3.0)
